christoffel/__init__.py
christoffel/christoffel.py
christoffel-0.0.1.dist-info/licenses/LICENSE
christoffel-0.0.1.dist-info/METADATA
christoffel-0.0.1.dist-info/WHEEL
christoffel-0.0.1.dist-info/top_level.txt
christoffel-0.0.1.dist-info/RECORD
