Metadata-Version: 2.4
Name: christoffel
Version: 0.0.1
Summary: Solving the Christoffel equation to calculate wave velocities from elastic properties
Home-page: https://github.com/Luka140/christoffel/tree/release
Author: Jan Jaeken
Author-email: jan.jaeken@gmail.com
Maintainer-email: luka-groot@hotmail.nl
License: GNU General Public License v3.0
Classifier: Programming Language :: Python :: 3.12
Classifier: Operating System :: OS Independent
License-File: LICENSE
Requires-Dist: numpy
Dynamic: author
Dynamic: author-email
Dynamic: classifier
Dynamic: description
Dynamic: description-content-type
Dynamic: home-page
Dynamic: license
Dynamic: license-file
Dynamic: maintainer-email
Dynamic: requires-dist
Dynamic: summary
